immunx_agent/__init__.py
immunx_agent/alert.py
immunx_agent/alert_event.py
immunx_agent/alert_test.py
immunx_agent/block.py
immunx_agent/block_event.py
immunx_agent/bloom_filter.py
immunx_agent/bloom_filter_test.py
immunx_agent/event_type.py
immunx_agent/finding.py
immunx_agent/immunx_graphql.py
immunx_agent/jwt.py
immunx_agent/jwt_test.py
immunx_agent/label.py
immunx_agent/network.py
immunx_agent/receipt.py
immunx_agent/trace.py
immunx_agent/transaction.py
immunx_agent/transaction_event.py
immunx_agent/utils.py
immunx_agent-0.0.1.dist-info/LICENSE
immunx_agent-0.0.1.dist-info/METADATA
immunx_agent-0.0.1.dist-info/WHEEL
immunx_agent-0.0.1.dist-info/top_level.txt
immunx_agent-0.0.1.dist-info/RECORD
