Metadata-Version: 2.1
Name: immunx-agent
Version: 0.0.1
Summary: Immunx Agent Python SDK
Home-page: https://immunx.numencyber.com
Project-URL: Source, https://github.com/786967951/immunx-agent-sdk
Project-URL: Documentation, https://github.com/786967951/immunx-agent-sdk
Classifier: Programming Language :: Python :: 3
Classifier: License :: OSI Approved :: MIT License
Classifier: Operating System :: OS Independent
Requires-Python: >=3.6
License-File: LICENSE
Requires-Dist: jsonc-parser
Requires-Dist: web3 (==5.23.0)
Requires-Dist: hexbytes
Requires-Dist: mmh3 (==3.0.0)
